LICENCE
MANIFEST.in
README.rst
setup.cfg
setup.py
pylogd/__init__.py
pylogd/handlers.py
pylogd/stats.py
pylogd.egg-info/PKG-INFO
pylogd.egg-info/SOURCES.txt
pylogd.egg-info/dependency_links.txt
pylogd.egg-info/entry_points.txt
pylogd.egg-info/not-zip-safe
pylogd.egg-info/requires.txt
pylogd.egg-info/top_level.txt
pylogd/twisted/__init__.py
pylogd/twisted/handlers.py
pylogd/twisted/socket.py
pylogd/twisted/stats.py