Metadata-Version: 1.0
Name: pylogd
Version: 0.2
Summary: logd python library
Home-page: 'http://github.com/hiidef/logd'
Author: Jason Moiron
Author-email: jason@hiidef.com
License: MIT
Keywords: logd python udp logging server client
Platform: UNKNOWN
Classifier: Development Status :: 4 - Beta
Classifier: License :: OSI Approved :: MIT License
Classifier: Intended Audience :: Developers
